pytest_rca_report-0.1.3.dist-info/licenses/LICENSE
rca_report/__init__.py
rca_report/parser.py
rca_report/assets/index.html
rca_report/assets/static/css/style.css
rca_report/assets/static/js/app.js
pytest_rca_report-0.1.3.dist-info/METADATA
pytest_rca_report-0.1.3.dist-info/WHEEL
pytest_rca_report-0.1.3.dist-info/entry_points.txt
pytest_rca_report-0.1.3.dist-info/top_level.txt
pytest_rca_report-0.1.3.dist-info/RECORD
