Metadata-Version: 2.4
Name: pytest-rca-report
Version: 0.1.3
Summary: Interactive RCA report generator for pytest runs, with AI-based analysis and visual dashboard
Author-email: Keinar Elkayam <keinar.elkayam@kaleidoo.ai>
License: MIT
Project-URL: Homepage, https://github.com/keinar/pytest-rca-report
Project-URL: Repository, https://github.com/keinar/pytest-rca-report
Requires-Python: >=3.9
License-File: LICENSE
Requires-Dist: matplotlib
Requires-Dist: numpy
Requires-Dist: python-dotenv
Requires-Dist: openai
Dynamic: license-file
